deepnlpf/__init__.py
deepnlpf/__main__.py
deepnlpf/_version.py
deepnlpf/config.ini
deepnlpf/config.py
deepnlpf/data.log
deepnlpf/dataset.py
deepnlpf/global_parameters.py
deepnlpf/iplugindb.py
deepnlpf/log.py
deepnlpf/mongoflask.py
deepnlpf/pipeline.py
deepnlpf/preprocessing.py
deepnlpf/statistics.py
deepnlpf/core/__init__.py
deepnlpf/core/api_antiga.py
deepnlpf/core/boost.py
deepnlpf/core/execute.py
deepnlpf/core/gazzetter.py
deepnlpf/core/iplugin.py
deepnlpf/core/output_format.py
deepnlpf/core/plugin_manager.py
deepnlpf/core/util.py
deepnlpf/dashboard/__init__.py
deepnlpf/dashboard/__main__.py
deepnlpf/dashboard/config.py
deepnlpf/dashboard/app/__init__.py
deepnlpf/dashboard/app/views/__init__.py
deepnlpf/dashboard/app/views/views.py
deepnlpf/helpers/__init__.py
deepnlpf/helpers/mongodb.py
deepnlpf/helpers/freeling_api_py3/__init__.py
deepnlpf/helpers/freeling_api_py3/pyfreeling.py
deepnlpf/models/__init__.py
deepnlpf/models/mongodb.py
deepnlpf/models/statistics.py
deepnlpf/modules/__init__.py
deepnlpf/modules/stopwords/__init__.py
deepnlpf/modules/utils/Email.py
deepnlpf/modules/utils/__init__.py
deepnlpf/modules/utils/preprocessing.py
deepnlpf/notifications/__init__.py
deepnlpf/notifications/email.py
deepnlpf/notifications/telegram.py
deepnlpf/notifications/toast.py
deepnlpf/templates/__init__.py
deepnlpf/templates/schema.py
deepnlpf/util/__init__.py
deepnlpf/util/encoder.py
deepnlpf/util/random_object_id.py
deepnlpf-0.0.20.dist-info/LICENSE
deepnlpf-0.0.20.dist-info/METADATA
deepnlpf-0.0.20.dist-info/WHEEL
deepnlpf-0.0.20.dist-info/entry_points.txt
deepnlpf-0.0.20.dist-info/top_level.txt
deepnlpf-0.0.20.dist-info/RECORD
